tools.py
pytestlib/__init__.py
pytestlib/firstpackage.py
pytestlib-1.0.0.dist-info/LICENSE.txt
pytestlib-1.0.0.dist-info/METADATA
pytestlib-1.0.0.dist-info/WHEEL
pytestlib-1.0.0.dist-info/top_level.txt
pytestlib-1.0.0.dist-info/RECORD
