Metadata-Version: 2.1
Name: pytestlib
Version: 1.0.0
Summary: this is the first zhao's lib
Home-page: https://github.com
Author: zhao
Author-email: xxxx@xxxx.com
License-File: LICENSE.txt
